setup.cfg
setup.py
PyDatagateway.egg-info/PKG-INFO
PyDatagateway.egg-info/SOURCES.txt
PyDatagateway.egg-info/dependency_links.txt
PyDatagateway.egg-info/entry_points.txt
PyDatagateway.egg-info/requires.txt
PyDatagateway.egg-info/top_level.txt
TCLIService/TCLIService.py
TCLIService/__init__.py
TCLIService/constants.py
TCLIService/ttypes.py
pydatagateway/__init__.py
pydatagateway/common.py
pydatagateway/datagateway.py
pydatagateway/exc.py
pydatagateway/hive.py
pydatagateway/presto.py
pydatagateway/sqlalchemy_backports.py
pydatagateway/sqlalchemy_hive.py
pydatagateway/sqlalchemy_presto.py