Metadata-Version: 1.1
Name: PyDatagateway
Version: 0.1.5
Summary: Python interface to Datagateway
Home-page: https://github.com/yanyu-singapore/PyDatagateway.git
Author: Yanyu Qu
Author-email: yanyuqu@gmail.com
License: Apache License, Version 2.0
Platform: UNKNOWN
Classifier: Intended Audience :: Developers
Classifier: License :: OSI Approved :: Apache Software License
Classifier: Operating System :: OS Independent
Classifier: Topic :: Database :: Front-Ends
